fastapi_ndjson_logger/__init__.py
fastapi_ndjson_logger/fastapi_ndjson_logger.py
fastapi_ndjson_logger-0.1.3.dist-info/LICENSE
fastapi_ndjson_logger-0.1.3.dist-info/METADATA
fastapi_ndjson_logger-0.1.3.dist-info/WHEEL
fastapi_ndjson_logger-0.1.3.dist-info/top_level.txt
fastapi_ndjson_logger-0.1.3.dist-info/RECORD
