Metadata-Version: 2.1
Name: fastapi_ndjson_logger
Version: 0.1.3
Summary: A FastAPI middleware for logging requests and responses in NDJSON format
Home-page: https://github.com/analogdata/fastapi-logger
Author: Rajath Kumar
Author-email: rajathkumarks@gmail.com
License: MIT
Classifier: Development Status :: 2 - Pre-Alpha
Classifier: Intended Audience :: Developers
Classifier: License :: OSI Approved :: MIT License
Classifier: Programming Language :: Python :: 3
Classifier: Operating System :: OS Independent
Classifier: Framework :: FastAPI
Requires-Python: >=3.12
License-File: LICENSE
Requires-Dist: fastapi
